[
  {
    "objectid": "735318",
    "applicant": "Ziaurehman Amini",
    "facilitytype": "Push Cart",
    "cnn": "30727000",
    "locationdescription": "MARKET ST: DRUMM ST intersection",
    "address": "5 THE EMBARCADERO",
    "blocklot": "0234017",
    "block": "0234",
    "lot": "017",
    "permit": "15MFF-0159",
    "status": "REQUESTED",
    "x": "6013916.72",
    "y": "2117244.027",
    "latitude": "37.794331003246846",
    "longitude": "-122.39581105302317",
    "schedule": "http://bsm.sfdpw.org/PermitsTracker/reports/report.aspx?title=schedule&report=rptSchedule&params=permit=15MFF-0159&ExportPDF=1&Filename=15MFF-0159_schedule.pdf",
    "received": "20151231",
    "priorpermit": "0",
    "expirationdate": "2016-03-15T00:00:00.000",
    "location":
    {
      "latitude": "37.794331003246846",
      "longitude": "-122.39581105302317",
      "human_address": "{\"address\": \"\", \"city\": \"\", \"state\": \"\", \"zip\": \"\"}"
    },
    ":@computed_region_yftq_j783": "4",
    ":@computed_region_p5aj_wyqh": "1",
    ":@computed_region_rxqg_mtj9": "10",
    ":@computed_region_bh8s_q3mv": "28855",
    ":@computed_region_fyvs_ahh9": "6"
  },
  {
    "objectid": "1587541",
    "applicant": "Brazuca Grill",
    "facilitytype": "Truck",
    "cnn": "1232000",
    "address": "601 23RD ST",
    "blocklot": "4232010",
    "block": "4232",
    "lot": "010",
    "permit": "21MFF-00154",
    "status": "EXPIRED",
    "fooditems": "Cold Truck: Sandwiches: Noodles:  Pre-packaged Snacks: Candy: Desserts Various Beverages",
    "x": "6016887.317",
    "y": "2102871.037",
    "latitude": "37.755030726766726",
    "longitude": "-122.38453073422282",
    "schedule": "http://bsm.sfdpw.org/PermitsTracker/reports/report.aspx?title=schedule&report=rptSchedule&params=permit=21MFF-00154&ExportPDF=1&Filename=21MFF-00154_schedule.pdf",
    "approved": "2021-12-30T00:00:00.000",
    "received": "20211230",
    "priorpermit": "1",
    "expirationdate": "2022-11-15T00:00:00.000",
    "location":
    {
      "latitude": "37.755030726766726",
      "longitude": "-122.38453073422282",
      "human_address": "{\"address\": \"\", \"city\": \"\", \"state\": \"\", \"zip\": \"\"}"
    },
    ":@computed_region_yftq_j783": "10",
    ":@computed_region_p5aj_wyqh": "3",
    ":@computed_region_rxqg_mtj9": "8",
    ":@computed_region_bh8s_q3mv": "28856",
    ":@computed_region_fyvs_ahh9": "29"
  },
  {
    "objectid": "1612654",
    "applicant": "Sunset Mercantile/Outer Sunset Farmers Market & Mercantile",
    "facilitytype": "Truck",
    "cnn": "1835000",
    "locationdescription": "37TH AVE: QUINTARA ST to RIVERA ST (2100 - 2199)",
    "address": "2155 37TH AVE",
    "blocklot": "2094006",
    "block": "2094",
    "lot": "006",
    "permit": "22MFF-00031",
    "status": "REQUESTED",
    "fooditems": "Multiple Food Trucks & Food Types",
    "x": "5984527.62",
    "y": "2100736.237",
    "latitude": "37.74732654654123",
    "longitude": "-122.49628067270531",
    "schedule": "http://bsm.sfdpw.org/PermitsTracker/reports/report.aspx?title=schedule&report=rptSchedule&params=permit=22MFF-00031&ExportPDF=1&Filename=22MFF-00031_schedule.pdf",
    "received": "20220421",
    "priorpermit": "0",
    "expirationdate": "2022-11-15T00:00:00.000",
    "location":
    {
      "latitude": "37.74732654654123",
      "longitude": "-122.49628067270531",
      "human_address": "{\"address\": \"\", \"city\": \"\", \"state\": \"\", \"zip\": \"\"}"
    },
    ":@computed_region_yftq_j783": "1",
    ":@computed_region_p5aj_wyqh": "8",
    ":@computed_region_rxqg_mtj9": "3",
    ":@computed_region_bh8s_q3mv": "29491",
    ":@computed_region_fyvs_ahh9": "35"
  },
  {
    "objectid": "1587567",
    "applicant": "Brazuca Grill",
    "facilitytype": "Truck",
    "cnn": "8714000",
    "locationdescription": "MARIPOSA ST: TENNESSEE ST to 04TH ST \\ MINNESOTA ST (600 - 699)",
    "address": "601 MARIPOSA ST",
    "blocklot": "3996013",
    "block": "3996",
    "lot": "013",
    "permit": "21MFF-00154",
    "status": "EXPIRED",
    "fooditems": "Cold Truck: Sandwiches: Noodles:  Pre-packaged Snacks: Candy: Desserts Various Beverages",
    "x": "6015331.083",
    "y": "2106187.955",
    "latitude": "37.764052089924235",
    "longitude": "-122.39014439398791",
    "schedule": "http://bsm.sfdpw.org/PermitsTracker/reports/report.aspx?title=schedule&report=rptSchedule&params=permit=21MFF-00154&ExportPDF=1&Filename=21MFF-00154_schedule.pdf",
    "approved": "2021-12-30T00:00:00.000",
    "received": "20211230",
    "priorpermit": "1",
    "expirationdate": "2022-11-15T00:00:00.000",
    "location":
    {
      "latitude": "37.764052089924235",
      "longitude": "-122.39014439398791",
      "human_address": "{\"address\": \"\", \"city\": \"\", \"state\": \"\", \"zip\": \"\"}"
    },
    ":@computed_region_yftq_j783": "14",
    ":@computed_region_p5aj_wyqh": "3",
    ":@computed_region_rxqg_mtj9": "8",
    ":@computed_region_bh8s_q3mv": "28856",
    ":@computed_region_fyvs_ahh9": "29"
  },
  {
    "objectid": "1587393",
    "applicant": "Truly Food & More",
    "facilitytype": "Truck",
    "cnn": "6148201",
    "locationdescription": "GENEVA AVE: PRAGUE ST to LINDA VISTA STPS (1500 - 1598) -- SOUTH --",
    "address": "1500 GENEVA AVE",
    "blocklot": "6418065",
    "block": "6418",
    "lot": "065",
    "permit": "21MFF-00151",
    "status": "REQUESTED",
    "fooditems": "Latin Food: Tacos: Pupusas: Vegetables: Salad: Water: Sodas",
    "x": "6002948.585",
    "y": "2087593.93",
    "latitude": "37.712302604744416",
    "longitude": "-122.43164419037294",
    "schedule": "http://bsm.sfdpw.org/PermitsTracker/reports/report.aspx?title=schedule&report=rptSchedule&params=permit=21MFF-00151&ExportPDF=1&Filename=21MFF-00151_schedule.pdf",
    "received": "20211229",
    "priorpermit": "0",
    "expirationdate": "2022-11-15T00:00:00.000",
    "location":
    {
      "latitude": "37.712302604744416",
      "longitude": "-122.43164419037294",
      "human_address": "{\"address\": \"\", \"city\": \"\", \"state\": \"\", \"zip\": \"\"}"
    },
    ":@computed_region_yftq_j783": "9",
    ":@computed_region_p5aj_wyqh": "7",
    ":@computed_region_rxqg_mtj9": "6",
    ":@computed_region_bh8s_q3mv": "28861",
    ":@computed_region_fyvs_ahh9": "5"
  },
  {
    "objectid": "1621287",
    "applicant": "Street Meet",
    "facilitytype": "Truck",
    "cnn": "13057001",
    "locationdescription": "VALENCIA ST: 14TH ST to ROSA PARKS LN (300 - 337)",
    "address": "306 VALENCIA ST",
    "blocklot": "3546001",
    "block": "3546",
    "lot": "001",
    "permit": "22MFF-00033",
    "status": "REQUESTED",
    "fooditems": "Burritos: Tacos: Tortas: Quesadillas & Various Drinks.",
    "x": "6006013.135",
    "y": "2107762.89",
    "latitude": "37.767855269354264",
    "longitude": "-122.42248440416165",
    "schedule": "http://bsm.sfdpw.org/PermitsTracker/reports/report.aspx?title=schedule&report=rptSchedule&params=permit=22MFF-00033&ExportPDF=1&Filename=22MFF-00033_schedule.pdf",
    "approved": "2019-09-06T00:00:00.000",
    "received": "20220602",
    "priorpermit": "0",
    "expirationdate": "2021-01-15T00:00:00.000",
    "location":
    {
      "latitude": "37.767855269354264",
      "longitude": "-122.42248440416165",
      "human_address": "{\"address\": \"\", \"city\": \"\", \"state\": \"\", \"zip\": \"\"}"
    },
    ":@computed_region_yftq_j783": "8",
    ":@computed_region_p5aj_wyqh": "4",
    ":@computed_region_rxqg_mtj9": "5",
    ":@computed_region_bh8s_q3mv": "28853",
    ":@computed_region_fyvs_ahh9": "19"
  },
  {
    "objectid": "1591840",
    "applicant": "Tacos Rodriguez",
    "facilitytype": "Truck",
    "cnn": "5331101",
    "locationdescription": "EVANS AVE: KEITH ST to MENDELL ST (1201 - 1399) -- SOUTH --",
    "address": "1275 EVANS AVE",
    "blocklot": "5237033",
    "block": "5237",
    "lot": "033",
    "permit": "22MFF-00024",
    "status": "SUSPEND",
    "fooditems": "Tacos: burritos: quesadillas: soda & water",
    "x": "6017367.817",
    "y": "2097063.665",
    "latitude": "37.73911142974502",
    "longitude": "-122.38246497113636",
    "schedule": "http://bsm.sfdpw.org/PermitsTracker/reports/report.aspx?title=schedule&report=rptSchedule&params=permit=22MFF-00024&ExportPDF=1&Filename=22MFF-00024_schedule.pdf",
    "received": "20220126",
    "priorpermit": "1",
    "expirationdate": "2022-11-15T00:00:00.000",
    "location":
    {
      "latitude": "37.73911142974502",
      "longitude": "-122.38246497113636",
      "human_address": "{\"address\": \"\", \"city\": \"\", \"state\": \"\", \"zip\": \"\"}"
    },
    ":@computed_region_yftq_j783": "10",
    ":@computed_region_p5aj_wyqh": "3",
    ":@computed_region_rxqg_mtj9": "8",
    ":@computed_region_bh8s_q3mv": "58",
    ":@computed_region_fyvs_ahh9": "1"
  },
  {
    "objectid": "1591842",
    "applicant": "Tacos Rodriguez",
    "facilitytype": "Truck",
    "cnn": "9794000",
    "locationdescription": "OAKDALE AVE: INDUSTRIAL ST \\ SELBY ST to TOLAND ST (2100 - 2199)",
    "address": "2198 OAKDALE AVE",
    "blocklot": "5590A008",
    "block": "5590A",
    "lot": "008",
    "permit": "22MFF-00024",
    "status": "SUSPEND",
    "fooditems": "Tacos: burritos: quesadillas: soda & water",
    "x": "6011973.411",
    "y": "2097858.615",
    "latitude": "37.74099473500238",
    "longitude": "-122.4011723353864",
    "schedule": "http://bsm.sfdpw.org/PermitsTracker/reports/report.aspx?title=schedule&report=rptSchedule&params=permit=22MFF-00024&ExportPDF=1&Filename=22MFF-00024_schedule.pdf",
    "received": "20220126",
    "priorpermit": "1",
    "expirationdate": "2022-11-15T00:00:00.000",
    "location":
    {
      "latitude": "37.74099473500238",
      "longitude": "-122.4011723353864",
      "human_address": "{\"address\": \"\", \"city\": \"\", \"state\": \"\", \"zip\": \"\"}"
    },
    ":@computed_region_yftq_j783": "10",
    ":@computed_region_p5aj_wyqh": "3",
    ":@computed_region_rxqg_mtj9": "8",
    ":@computed_region_bh8s_q3mv": "58",
    ":@computed_region_fyvs_ahh9": "1"
  },
  {
    "objectid": "1591841",
    "applicant": "Tacos Rodriguez",
    "facilitytype": "Truck",
    "cnn": "8958000",
    "locationdescription": "MENDELL ST: GALVEZ AVE to HUDSON AVE (600 - 699)",
    "address": "600 MENDELL ST",
    "blocklot": "5254037",
    "block": "5254",
    "lot": "037",
    "permit": "22MFF-00024",
    "status": "SUSPEND",
    "fooditems": "Tacos: burritos: quesadillas: soda & water",
    "x": "6016207.357",
    "y": "2097293.665",
    "latitude": "37.73967879180792",
    "longitude": "-122.38649338455488",
    "schedule": "http://bsm.sfdpw.org/PermitsTracker/reports/report.aspx?title=schedule&report=rptSchedule&params=permit=22MFF-00024&ExportPDF=1&Filename=22MFF-00024_schedule.pdf",
    "received": "20220126",
    "priorpermit": "1",
    "expirationdate": "2022-11-15T00:00:00.000",
    "location":
    {
      "latitude": "37.73967879180792",
      "longitude": "-122.38649338455488",
      "human_address": "{\"address\": \"\", \"city\": \"\", \"state\": \"\", \"zip\": \"\"}"
    },
    ":@computed_region_yftq_j783": "10",
    ":@computed_region_p5aj_wyqh": "3",
    ":@computed_region_rxqg_mtj9": "8",
    ":@computed_region_bh8s_q3mv": "58",
    ":@computed_region_fyvs_ahh9": "1"
  },
  {
    "objectid": "1591839",
    "applicant": "Tacos Rodriguez",
    "facilitytype": "Truck",
    "cnn": "11542000",
    "locationdescription": "SANSOME ST: SUTTER ST to BUSH ST (1 - 99)",
    "address": "1 SANSOME ST",
    "blocklot": "0289003",
    "block": "0289",
    "lot": "003",
    "permit": "22MFF-00024",
    "status": "SUSPEND",
    "fooditems": "Tacos: burritos: quesadillas: soda & water",
    "x": "6012406.465",
    "y": "2115874.016",
    "latitude": "37.790485146128",
    "longitude": "-122.40094044068951",
    "schedule": "http://bsm.sfdpw.org/PermitsTracker/reports/report.aspx?title=schedule&report=rptSchedule&params=permit=22MFF-00024&ExportPDF=1&Filename=22MFF-00024_schedule.pdf",
    "received": "20220126",
    "priorpermit": "1",
    "expirationdate": "2022-11-15T00:00:00.000",
    "location":
    {
      "latitude": "37.790485146128",
      "longitude": "-122.40094044068951",
      "human_address": "{\"address\": \"\", \"city\": \"\", \"state\": \"\", \"zip\": \"\"}"
    },
    ":@computed_region_yftq_j783": "4",
    ":@computed_region_p5aj_wyqh": "1",
    ":@computed_region_rxqg_mtj9": "10",
    ":@computed_region_bh8s_q3mv": "28854",
    ":@computed_region_fyvs_ahh9": "6"
  }
]
